stopwords_tr/__init__.py
stopwords_tr-2.0.1.dist-info/LICENSE
stopwords_tr-2.0.1.dist-info/METADATA
stopwords_tr-2.0.1.dist-info/WHEEL
stopwords_tr-2.0.1.dist-info/top_level.txt
stopwords_tr-2.0.1.dist-info/RECORD
